<?xml version = '1.0' encoding = 'UTF-8'?>
<TableProxySqlServerv2k class="oracle.dbtools.crest.model.design.storage.sqlserver.v2k.TableProxySqlServerv2k" name="sales" directorySegmentName="seg_0" id="2E53191C-3B03-620F-794D-3FB40440AD7E">
<createdBy>Giuseppe</createdBy>
<createdTime>2025-01-23 11:07:15 UTC</createdTime>
<ownerDesignName>visualization</ownerDesignName>
<database>DB_NULLELEMENT</database>
<columnProxies>
<ColumnProxy class="oracle.dbtools.crest.model.design.storage.sqlserver.v2k.ColumnProxySqlServerv2k" name="prod_id" id="87BD820F-FCFB-C310-C298-979E78F4B1D6">
<createdBy>Giuseppe</createdBy>
<createdTime>2025-01-23 11:07:15 UTC</createdTime>
<ownerDesignName>visualization</ownerDesignName>
</ColumnProxy>
<ColumnProxy class="oracle.dbtools.crest.model.design.storage.sqlserver.v2k.ColumnProxySqlServerv2k" name="promo_id" id="9904596E-9DC7-CAA3-5853-DCC3C475F4A5">
<createdBy>Giuseppe</createdBy>
<createdTime>2025-01-23 11:07:15 UTC</createdTime>
<ownerDesignName>visualization</ownerDesignName>
</ColumnProxy>
<ColumnProxy class="oracle.dbtools.crest.model.design.storage.sqlserver.v2k.ColumnProxySqlServerv2k" name="time_id" id="ADF694A4-59FB-EEE5-12BA-9A0BF348C015">
<createdBy>Giuseppe</createdBy>
<createdTime>2025-01-23 11:07:15 UTC</createdTime>
<ownerDesignName>visualization</ownerDesignName>
</ColumnProxy>
<ColumnProxy class="oracle.dbtools.crest.model.design.storage.sqlserver.v2k.ColumnProxySqlServerv2k" name="quantity_sold" id="B9F80D3D-DEF4-5C4A-482D-1D4848D57AF2">
<createdBy>Giuseppe</createdBy>
<createdTime>2025-01-23 11:07:15 UTC</createdTime>
<ownerDesignName>visualization</ownerDesignName>
</ColumnProxy>
<ColumnProxy class="oracle.dbtools.crest.model.design.storage.sqlserver.v2k.ColumnProxySqlServerv2k" name="amount_sold" id="E94267F7-B95E-0557-8B67-6AD2D4A5AB56">
<createdBy>Giuseppe</createdBy>
<createdTime>2025-01-23 11:07:15 UTC</createdTime>
<ownerDesignName>visualization</ownerDesignName>
</ColumnProxy>
<ColumnProxy class="oracle.dbtools.crest.model.design.storage.sqlserver.v2k.ColumnProxySqlServerv2k" name="cust_id" id="F160C876-E3C5-DFEC-A679-D88CC745B0CF">
<createdBy>Giuseppe</createdBy>
<createdTime>2025-01-23 11:07:15 UTC</createdTime>
<ownerDesignName>visualization</ownerDesignName>
</ColumnProxy>
<ColumnProxy class="oracle.dbtools.crest.model.design.storage.sqlserver.v2k.ColumnProxySqlServerv2k" name="channel_id" id="FE884A31-1D4A-27E0-B490-65C8344B9C4F">
<createdBy>Giuseppe</createdBy>
<createdTime>2025-01-23 11:07:15 UTC</createdTime>
<ownerDesignName>visualization</ownerDesignName>
</ColumnProxy>
</columnProxies>
<foreignKeys>
<ForeignKey class="oracle.dbtools.crest.model.design.storage.sqlserver.v2k.FKProxySqlServerv2k" name="sales_FK0" id="E1162AAE-FB25-79E3-7B0D-D4961C1350E9">
<createdBy>Giuseppe</createdBy>
<createdTime>2025-01-23 11:07:15 UTC</createdTime>
<ownerDesignName>visualization</ownerDesignName>
</ForeignKey>
</foreignKeys>
<primaryKeys>
<PrimaryKey class="oracle.dbtools.crest.model.design.storage.sqlserver.v2k.PKProxySqlServerv2k" name="sales__IDXv4" id="F9BDF1BC-984F-25A1-F2F1-74DC353A0B6D">
<createdBy>Giuseppe</createdBy>
<createdTime>2025-01-23 11:07:15 UTC</createdTime>
<ownerDesignName>visualization</ownerDesignName>
<clustered>true</clustered>
</PrimaryKey>
</primaryKeys>
<uniqueKeys>
<UniqueKey class="oracle.dbtools.crest.model.design.storage.sqlserver.v2k.UniqueProxySqlServerv2k" name="sales__IDX" id="12B91D46-E125-CD20-A74A-8957C8215EEA">
<createdBy>Giuseppe</createdBy>
<createdTime>2025-01-23 11:07:15 UTC</createdTime>
<ownerDesignName>visualization</ownerDesignName>
</UniqueKey>
<UniqueKey class="oracle.dbtools.crest.model.design.storage.sqlserver.v2k.UniqueProxySqlServerv2k" name="sales__IDXv2" id="435D28A3-FF80-2EE5-2B2B-65A35774E404">
<createdBy>Giuseppe</createdBy>
<createdTime>2025-01-23 11:07:15 UTC</createdTime>
<ownerDesignName>visualization</ownerDesignName>
</UniqueKey>
<UniqueKey class="oracle.dbtools.crest.model.design.storage.sqlserver.v2k.UniqueProxySqlServerv2k" name="sales__IDXv3" id="96066337-BCA9-6119-F17D-AC2B9641A753">
<createdBy>Giuseppe</createdBy>
<createdTime>2025-01-23 11:07:15 UTC</createdTime>
<ownerDesignName>visualization</ownerDesignName>
</UniqueKey>
<UniqueKey class="oracle.dbtools.crest.model.design.storage.sqlserver.v2k.UniqueProxySqlServerv2k" name="sales__IDXv1" id="AF0BA387-EE91-864E-C8AF-E5BFEBC0DB83">
<createdBy>Giuseppe</createdBy>
<createdTime>2025-01-23 11:07:15 UTC</createdTime>
<ownerDesignName>visualization</ownerDesignName>
</UniqueKey>
</uniqueKeys>
</TableProxySqlServerv2k>